ClickUptoS3Migration/__init__.py
clickup_to_s3_migration-1.1.1.dist-info/LICENSE
clickup_to_s3_migration-1.1.1.dist-info/METADATA
clickup_to_s3_migration-1.1.1.dist-info/WHEEL
clickup_to_s3_migration-1.1.1.dist-info/top_level.txt
clickup_to_s3_migration-1.1.1.dist-info/RECORD
