Metadata-Version: 2.1
Name: clickup-to-s3-migration
Version: 1.1.1
Summary: My coworkers and I created this free and open-source library. Anyone can now transfer entire clicks folders, tickets, and comments to AWS S3. When we switched from Clickup to JIRA software, this task was essentially done to backup the entire Clickup system. This threaded script employs the maximum number of threads to use ClickUP APIS and migrate all data into Data Lake S3 so that users or teams can use Athena to query using regular SQL if necessary. 
Home-page: https://github.com/soumilshah1995/clickup_to_s3_migration
Author: Soumil Nitin Shah
Author-email: shahsoumil519@gmail.com
License: MIT
Platform: UNKNOWN
Classifier: License :: OSI Approved :: MIT License
Classifier: Programming Language :: Python :: 3
Classifier: Programming Language :: Python :: 3.7
License-File: LICENSE
Requires-Dist: boto3
Requires-Dist: tqdm
